smolvladataset/__init__.py
smolvladataset/build.py
smolvladataset/cache.py
smolvladataset/dataset.py
smolvladataset/utils.py
smolvladataset/data/datasets.csv
smolvladataset-0.1.1.dist-info/licenses/LICENSE
smolvladataset-0.1.1.dist-info/METADATA
smolvladataset-0.1.1.dist-info/WHEEL
smolvladataset-0.1.1.dist-info/top_level.txt
smolvladataset-0.1.1.dist-info/RECORD
