Metadata-Version: 2.4
Name: smolvladataset
Version: 0.1.1
Summary: Loader for SmolVLA robotics datasets with deterministic train/val/test splits; LeRobot‑compatible, cached locally, downloads precompiled bundles from the Hugging Face Hub or rebuilds from a CSV.
Author: franklintra, bonsainoodle
Project-URL: GitHub, https://github.com/smolvladataset/smolvladataset
Project-URL: Dataset, https://huggingface.co/datasets/SmolVLADataset/SmolVLADataset
Keywords: dataset,robotics,dataset-loader,smolvla,vision-language-action,lerobot,huggingface,machine-learning,robotics-datasets,ai-datasets
Requires-Python: >=3.11
License-File: LICENSE
Requires-Dist: numpy>=1.24
Requires-Dist: pandas>=2.3.2
Requires-Dist: pyarrow>=14.0.1
Requires-Dist: datasets>=2.0.0
Requires-Dist: huggingface-hub>=0.34.4
Requires-Dist: lerobot>=0.3.3
Provides-Extra: publish
Requires-Dist: python-dotenv>=1.0.0; extra == "publish"
Provides-Extra: dev
Requires-Dist: ruff>=0.4.0; extra == "dev"
Requires-Dist: ipykernel>=6.0.0; extra == "dev"
Dynamic: license-file
